dataclocklib/__init__.py
dataclocklib/charts.py
dataclocklib/exceptions.py
dataclocklib/typing.py
dataclocklib/utility.py
dataclocklib/config/dataclock.ini
dataclocklib/config/linechart.ini
dataclocklib-0.2.0.dist-info/METADATA
dataclocklib-0.2.0.dist-info/WHEEL
dataclocklib-0.2.0.dist-info/top_level.txt
dataclocklib-0.2.0.dist-info/RECORD
