Metadata-Version: 2.2
Name: dataclocklib
Version: 0.2.0
Summary: Data clock charts using matplotlib.
Author-email: Andrew Ridyard <andrew.ridyard@proton.me>
Maintainer-email: Andrew Ridyard <andrew.ridyard@proton.me>
License: # GNU GENERAL PUBLIC LICENSE
Project-URL: Repository, https://github.com/andyrids/dataclocklib
Project-URL: Issues, https://github.com/andyrids/dataclocklib/issues
Project-URL: Documentation, https://andyrids.github.io/dataclocklib/
Project-URL: Changelog, https://github.com/andyrids/dataclocklib/blob/main/CHANGELOG.md
Keywords: matplotlib,dataclock,visualisation,analysis
Classifier: Development Status :: 5 - Production/Stable
Classifier: Framework :: Matplotlib
Classifier: Intended Audience :: Developers
Classifier: Intended Audience :: Science/Research
Classifier: License :: OSI Approved :: GNU General Public License v3 or later (GPLv3+)
Classifier: Natural Language :: English
Classifier: Operating System :: OS Independent
Classifier: Programming Language :: Python :: 3 :: Only
Classifier: Programming Language :: Python :: 3.10
Classifier: Programming Language :: Python :: 3.11
Classifier: Programming Language :: Python :: 3.12
Classifier: Programming Language :: Python :: 3.13
Classifier: Topic :: Software Development :: Libraries :: Python Modules
Requires-Python: >=3.10
Requires-Dist: matplotlib
Requires-Dist: pandas[parquet]>=2.2.2
Requires-Dist: pypalettes>=0.1.5
Provides-Extra: docs
Requires-Dist: sphinx>=8.1.3; extra == "docs"
Requires-Dist: sphinx-autobuild>=2024.10.3; extra == "docs"
Requires-Dist: sphinx-rtd-theme>=3.0.2; extra == "docs"
Requires-Dist: myst-nb>=1.1.2; extra == "docs"
